SpatialKappa/__init__.py
SpatialKappa/share/SpatialKappa/SpatialKappa-v2.1.4.jar
SpatialKappa/share/SpatialKappa/SpatialKappa-v2.1.5.jar
SpatialKappa/share/SpatialKappa/ant-antlr-3.2.jar
SpatialKappa/tests/__init__.py
SpatialKappa/tests/caPump.ka
SpatialKappa/tests/no_init.ka
SpatialKappa-2.1.5.dist-info/DESCRIPTION.rst
SpatialKappa-2.1.5.dist-info/METADATA
SpatialKappa-2.1.5.dist-info/RECORD
SpatialKappa-2.1.5.dist-info/WHEEL
SpatialKappa-2.1.5.dist-info/metadata.json
SpatialKappa-2.1.5.dist-info/top_level.txt
