Metadata-Version: 2.0
Name: SpatialKappa
Version: 2.1.5
Summary: Implementation of syntactic extension of Kappa to allow expression of location and transport in models
Home-page: https://github.com/davidcsterratt/SpatialKappa
Author: Donal Stewart, Anatoly Sorokin, David C Sterratt
Author-email: david.c.sterratt@ed.ac.uk
License: UNKNOWN
Platform: UNKNOWN
Classifier: Programming Language :: Python :: 2
Classifier: Programming Language :: Java
Classifier: License :: OSI Approved :: GNU General Public License v3 (GPLv3)
Classifier: Operating System :: OS Independent
Requires-Python: <3
Requires-Dist: py4j
